streamlit_webrtc/__init__.py
streamlit_webrtc/_compat.py
streamlit_webrtc/component.py
streamlit_webrtc/components_callbacks.py
streamlit_webrtc/config.py
streamlit_webrtc/credentials.py
streamlit_webrtc/eventloop.py
streamlit_webrtc/factory.py
streamlit_webrtc/mix.py
streamlit_webrtc/models.py
streamlit_webrtc/process.py
streamlit_webrtc/py.typed
streamlit_webrtc/receive.py
streamlit_webrtc/relay.py
streamlit_webrtc/server.py
streamlit_webrtc/session_info.py
streamlit_webrtc/shutdown.py
streamlit_webrtc/source.py
streamlit_webrtc/webrtc.py
streamlit_webrtc/frontend/dist/index.html
streamlit_webrtc/frontend/dist/assets/index-7f7Trh5u.js
streamlit_webrtc-0.63.5.dist-info/METADATA
streamlit_webrtc-0.63.5.dist-info/WHEEL
streamlit_webrtc-0.63.5.dist-info/licenses/LICENSE
streamlit_webrtc-0.63.5.dist-info/RECORD
