Metadata-Version: 2.4
Name: streamlit-webrtc
Version: 0.63.5
Summary: Real-time video and audio processing on Streamlit
Project-URL: Repository, https://github.com/whitphx/streamlit-webrtc
Author-email: "Yuichiro Tachibana (Tsuchiya)" <t.yic.yt@gmail.com>
License-Expression: MIT
License-File: LICENSE
Requires-Python: !=3.9.7,>=3.9
Requires-Dist: aioice>=0.10.1
Requires-Dist: aiortc>=1.11.0
Requires-Dist: packaging>=20.0
Requires-Dist: streamlit>=0.89.0
